users/__init__.py
users/account_urls.py
users/admin.py
users/apps.py
users/context_processors.py
users/forms.py
users/models.py
users/profile_urls.py
users/tests.py
users/urls.py
users/views.py
users/templates/auth/account.html
users/templates/auth/change_password.html
users/templates/auth/change_password_done.html
users/templates/auth/password_reset.html
users/templates/auth/password_reset_complete.html
users/templates/auth/password_reset_confirm.html
users/templates/auth/password_reset_done.html
users/templates/profile/form.html
users/templates/profile/form2.html
users/templates/profile/form3.html
users/templates/profile/form_address.html
users/templates/profile/form_location.html
users/templates/profile/profile.html
users/templates/profile/profile_bottom.html
users/templates/profile/profile_left.html
users/templates/profile/profile_right.html
users/views/__init__.py
users/views/profile.py
users/views/__pycache__/__init__.cpython-310.pyc
users/views/__pycache__/__init__.cpython-37.pyc
users/views/__pycache__/__init__.cpython-38.pyc
users/views/__pycache__/__init__.cpython-39.pyc
users/views/__pycache__/profile.cpython-310.pyc
users/views/__pycache__/profile.cpython-38.pyc
users/views/__pycache__/profile.cpython-39.pyc
django_ipghrms_users-1.3.dist-info/LICENSE
django_ipghrms_users-1.3.dist-info/METADATA
django_ipghrms_users-1.3.dist-info/WHEEL
django_ipghrms_users-1.3.dist-info/top_level.txt
django_ipghrms_users-1.3.dist-info/RECORD
