Metadata-Version: 2.1
Name: django-ipghrms-users
Version: 1.3
Summary: Django IPG HRMS APP users
Home-page: http://ipg.tl/
Author: Kinos
Author-email: info@kinos.tl
Maintainer: kinos
Maintainer-email: info@kinos.tl
License: MIT
Classifier: Environment :: Web Environment
Classifier: Framework :: Django
Classifier: Programming Language :: Python :: 3
Classifier: Programming Language :: Python :: 3.7
License-File: LICENSE
